pccg/CL.py
pccg/__init__.py
pccg/make_system.py
pccg/splines.py
pccg-0.0.3.dist-info/METADATA
pccg-0.0.3.dist-info/WHEEL
pccg-0.0.3.dist-info/licenses/LICENSE
pccg-0.0.3.dist-info/RECORD
