Metadata-Version: 2.4
Name: pccg
Version: 0.0.3
Summary: Add your description here
License-File: LICENSE
Requires-Python: >=3.12
Requires-Dist: matplotlib>=3.10.6
Requires-Dist: numpy>=2.3.2
Requires-Dist: scipy>=1.16.1
Requires-Dist: torch>=2.8.0
